odoo/addons/website_sale_vat_required/README.rst
odoo/addons/website_sale_vat_required/__init__.py
odoo/addons/website_sale_vat_required/__manifest__.py
odoo/addons/website_sale_vat_required/controllers/__init__.py
odoo/addons/website_sale_vat_required/controllers/main.py
odoo/addons/website_sale_vat_required/demo/demo_assets.xml
odoo/addons/website_sale_vat_required/i18n/ca.po
odoo/addons/website_sale_vat_required/i18n/es.po
odoo/addons/website_sale_vat_required/i18n/fr.po
odoo/addons/website_sale_vat_required/i18n/website_sale_vat_required.pot
odoo/addons/website_sale_vat_required/readme/CONTRIBUTORS.rst
odoo/addons/website_sale_vat_required/readme/DESCRIPTION.rst
odoo/addons/website_sale_vat_required/readme/USAGE.rst
odoo/addons/website_sale_vat_required/static/description/icon.png
odoo/addons/website_sale_vat_required/static/description/index.html
odoo/addons/website_sale_vat_required/static/src/js/website_sale_vat_required.tour.js
odoo/addons/website_sale_vat_required/tests/__init__.py
odoo/addons/website_sale_vat_required/tests/test_website_sale_vat_required.py
odoo/addons/website_sale_vat_required/views/templates.xml
odoo12_addon_website_sale_vat_required-12.0.1.0.1.dist-info/METADATA
odoo12_addon_website_sale_vat_required-12.0.1.0.1.dist-info/WHEEL
odoo12_addon_website_sale_vat_required-12.0.1.0.1.dist-info/top_level.txt
odoo12_addon_website_sale_vat_required-12.0.1.0.1.dist-info/RECORD
