Metadata-Version: 2.1
Name: odoo12-addon-website-sale-vat-required
Version: 12.0.1.0.1
Summary: VAT number required in checkout form
Home-page: https://github.com/OCA/e-commerce
Author: Agile Business Group, Tecnativa, Odoo Community Association (OCA)
Author-email: support@odoo-community.org
License: AGPL-3
Platform: UNKNOWN
Classifier: Programming Language :: Python
Classifier: Framework :: Odoo
Classifier: License :: OSI Approved :: GNU Affero General Public License v3
Requires-Python: >=3.5
Requires-Dist: odoo (<12.1dev,>=12.0a)
